urpy/__init__.py
urpy/rtde/__init__.py
urpy/rtde/rtde.py
urpy/rtde/rtde_config.py
urpy/rtde/serialize.py
urpy-1.2.0.dist-info/LICENSE
urpy-1.2.0.dist-info/METADATA
urpy-1.2.0.dist-info/WHEEL
urpy-1.2.0.dist-info/top_level.txt
urpy-1.2.0.dist-info/RECORD
