Metadata-Version: 2.1
Name: urpy
Version: 1.2.0
Summary: A simple to use library that can interface with Universal Robots UR robots.
Home-page: https://github.com/JonasAlmaas/urpy
Author: Jonas Almaas
Classifier: Programming Language :: Python :: 3
Classifier: License :: OSI Approved :: MIT License
Classifier: Operating System :: OS Independent
Requires-Python: >=3.6
License-File: LICENSE
